odoo10_addon_storage_file-10.0.1.1.2-py3.8-nspkg.pth
odoo/addons/storage_file/README.rst
odoo/addons/storage_file/__init__.py
odoo/addons/storage_file/__manifest__.py
odoo/addons/storage_file/controllers/__init__.py
odoo/addons/storage_file/controllers/main.py
odoo/addons/storage_file/data/ir_cron.xml
odoo/addons/storage_file/i18n/storage_file.pot
odoo/addons/storage_file/models/__init__.py
odoo/addons/storage_file/models/storage_backend.py
odoo/addons/storage_file/models/storage_file.py
odoo/addons/storage_file/security/ir.model.access.csv
odoo/addons/storage_file/security/storage_file.xml
odoo/addons/storage_file/static/description/icon.png
odoo/addons/storage_file/tests/__init__.py
odoo/addons/storage_file/tests/test_storage_file.py
odoo/addons/storage_file/views/storage_backend_view.xml
odoo/addons/storage_file/views/storage_file_view.xml
odoo10_addon_storage_file-10.0.1.1.2.dist-info/METADATA
odoo10_addon_storage_file-10.0.1.1.2.dist-info/WHEEL
odoo10_addon_storage_file-10.0.1.1.2.dist-info/namespace_packages.txt
odoo10_addon_storage_file-10.0.1.1.2.dist-info/top_level.txt
odoo10_addon_storage_file-10.0.1.1.2.dist-info/RECORD
